[
    {
        "id": 1388534400000,
        "author": "Pete Hunt",
        "text": "Hey there!"
    },
    {
        "id": 1420070400000,
        "author": "Paul O’Shannessy",
        "text": "React is *great*!"
    },
    {
        "id": 1420070400001,
        "author": "ChoseLa",
        "text": "Where am I"
    },
    {
        "id": 1453730914961,
        "author": "MFDOOM",
        "text": "The super vilain"
    },
    {
        "id": 1453731016353,
        "author": "Tyler",
        "text": "OFWGKTA"
    },
    {
        "id": 1453731032427,
        "author": "dcscsc",
        "text": "cdscs"
    },
    {
        "id": 1453731287363,
        "author": "TheMsn",
        "text": "yessir"
    },
    {
        "id": 1453731307498,
        "author": "superfastandfasta",
        "text": "balbalbalbalbalbalbla sodf at"
    },
    {
        "id": 1453819377551,
        "author": "working?",
        "text": "PLEASE!"
    }
]